vmo/__init__.py
vmo/generate.py
vmo/io.py
vmo/plot.py
vmo/test.py
vmo/VMO/__init__.py
vmo/VMO/oracle.py
vmo/VMO/utility/__init__.py
vmo/VMO/utility/misc.py
vmo/VMO/utility/distances/__init__.py
vmo/VMO/utility/distances/tonnetz.py
vmo/analysis/__init__.py
vmo/analysis/analysis.py
vmo/analysis/hmm.py
vmo/analysis/segmentation.py
vmo/realtime/__init__.py
vmo/realtime/tracker.py
vmo-0.30.4.dist-info/LICENSE
vmo-0.30.4.dist-info/METADATA
vmo-0.30.4.dist-info/WHEEL
vmo-0.30.4.dist-info/top_level.txt
vmo-0.30.4.dist-info/RECORD
