Metadata-Version: 2.1
Name: vmo
Version: 0.30.4
Summary: Variable Markov Oracle in Python
Home-page: https://github.com/wangsix/vmo
Author: Cheng-i Wang
Author-email: chw160@ucsd.edu
License: UNKNOWN
Project-URL: Bug Tracker, https://github.com/wangsix/vmo/issues
Platform: UNKNOWN
Classifier: Programming Language :: Python :: 3
Classifier: License :: OSI Approved :: GNU General Public License v3 (GPLv3)
Classifier: Operating System :: OS Independent
Requires-Python: >=3.7
License-File: LICENSE
